auto_graph/__init__.py
auto_graph/auto_graph.py
auto_graph/__private/__init__.py
auto_graph/__private/auto_graph_cpp.cp311-win_amd64.pyd
auto_graph/__private/auto_graph_cpp.cp312-win_amd64.pyd
auto_graph/__private/auto_graph_cpp.pyi
auto_graph/__private/auto_graph_cpp_d.pyi
pragmatic-0.4.dist-info/METADATA
pragmatic-0.4.dist-info/WHEEL
pragmatic-0.4.dist-info/top_level.txt
pragmatic-0.4.dist-info/RECORD
