Metadata-Version: 2.1
Name: pragmatic
Version: 0.4
Summary: C++ accelerated parts of auto_graph
